dbt_generator/__init__.py
dbt_generator/dbt_generator.py
dbt_generator/generate_base_models.py
dbt_generator/process_base_models.py
tests/__init__.py
tests/test_generate_base_models.py
tests/test_process_base_models.py
dbt_generator-0.3.2.dist-info/LICENSE
dbt_generator-0.3.2.dist-info/METADATA
dbt_generator-0.3.2.dist-info/WHEEL
dbt_generator-0.3.2.dist-info/entry_points.txt
dbt_generator-0.3.2.dist-info/top_level.txt
dbt_generator-0.3.2.dist-info/RECORD
