Metadata-Version: 2.1
Name: dbt-generator
Version: 0.3.2
Summary: Generate and process base models for dbt
Home-page: https://github.com/tuanchris/dbt-generator
Author: Tuan Nguyen
Author-email: anhtuan.nguyen@me.com
License: MIT
Keywords: dbt python package base models
Platform: UNKNOWN
Classifier: Programming Language :: Python :: 3
Classifier: License :: OSI Approved :: MIT License
Classifier: Operating System :: OS Independent
License-File: LICENSE
Requires-Dist: dbt-snowflake
Requires-Dist: dbt-bigquery
Requires-Dist: pyyaml
Requires-Dist: click
Requires-Dist: pytest
Requires-Dist: wordninja
